2023.3-2023.7/Functional Electronic Circuits/Lab3/mult.v
module mult(
    input clk_i,
    input rst_i,

    input [7:0] a_bi,
    input [7:0] b_bi,
    input start_i,

    output reg busy_o,
    output reg [15:0] y_bo
);

    localparam IDLE = 2'b00;
    localparam WORK = 2'b01;
    localparam END  = 2'b10;

    reg   [2:0] ctr;
    wire  [2:0] end_step;
    wire  [7:0] part_sum;
    wire [15:0] shifted_part_sum;
    reg   [7:0] a, b;
    reg  [15:0] part_res;
    reg   [1:0] state;

    assign part_sum = a & {8{b[ctr]}};
    assign shifted_part_sum = part_sum << ctr;

    always @(posedge clk_i)
        if (rst_i) begin
           ctr      <= 0;
           part_res <= 0;
           y_bo     <= 0;
           busy_o   <= 0;

           state <= IDLE;
        end else begin


            case (state)
                IDLE:
                    if (start_i) begin
                        state  <= WORK;

                        a        <= a_bi;
                        b        <= b_bi;
                        ctr      <= 0;
                        part_res <= 0;
                        busy_o   <= 1;
                    end
                WORK:
                    begin
                        if (ctr == 3'h7) begin
                            state  <= END;
                        end

                        part_res <= part_res + shifted_part_sum;
                        ctr <= ctr + 1;
                    end
                END: 
                    begin
                        y_bo   <= part_res;
                        busy_o <= 0;
                        state  <= IDLE;
                    end
                default: state <= IDLE;
            endcase
        end

endmodule

2023.3-2023.7/Functional Electronic Circuits/Lab5/example/adder.v
module adder (
    input [31:0] a_bi,
    input [31:0] b_bi,
    
    output [31:0] c_bo
);

assign c_bo = a_bi + b_bi;

endmodule

2023.3-2023.7/Functional Electronic Circuits/Lab3/dev.v
`include "adder.v"
`include "mult.v"
module dev (
    input clk_i,
    input rst_i,
    
    input [31:0] x_bi,
    input [31:0] y_bi,
    input start_i,
    
    output reg [31:0] y_bo,
    output reg rdy_o
);

reg signed [31:0] a1_op1, a1_op2;
reg signed [31:0] a2_op1, a2_op2;
wire signed [31:0] a1_res, a2_res;

adder a1(
    .a_bi(a1_op1),
    .b_bi(a1_op2),
    .c_bo(a1_res)    
);

adder a2(
    .a_bi(a2_op1),
    .b_bi(a2_op2),
    .c_bo(a2_res)    
);

reg [31:0] m1_op1, m1_op2, y1;
reg m1_start;
wire [15:0] m1_res16;
wire [31:0] m1_res = {16'h0, m1_res16};

mult m1 (
    .clk_i(clk_i),
    .rst_i(rst_i),
    .a_bi(m1_op1[7:0]),
    .b_bi(m1_op2[7:0]),
    .start_i(m1_start),
    .busy_o(m1_busy),
    .y_bo(m1_res16)
);

// FSM control unit code

localparam N = 32;

localparam IDLE               = 0;
localparam CMP_S              = 1;
localparam CALC_MULT_S1_START = 2;
localparam CALC_MULT_S1       = 3;
localparam CALC_MULT_S2_START = 4;
localparam CALC_MULT_S2       = 5;
localparam CALC_B             = 6;
localparam CMP_B              = 7;
localparam CALC_S             = 8;
localparam CALC_MULT_S3       = 9;
localparam FINISH_START       = 10;
localparam FINISH             = 11;

reg [3:0] state_r;
reg [31:0] x_r;
reg signed [31:0] s_r;
reg [31:0] y_r;
reg [31:0] b_r;

always@(posedge clk_i)
    if(rst_i) begin
        x_r <= 0;
        m1_op1 <= 0;
        m1_op2 <= 0;
        m1_start <= 0;
        a1_op1 <= 0;
        a1_op2 <= 0;
        a2_op1 <= 0;
        a2_op2 <= 0;
        y_bo   <= 0;
        y_r    <= 0;
        rdy_o  <= 1;
        s_r    <= 0;
        y1     <= 0;
        
        state_r <= IDLE;
        
    end else begin
        case(state_r)
            IDLE:
                if(start_i) begin
                    x_r <= x_bi;
                    y_r <= 0;
                    rdy_o <= 0;
                    b_r <= 0;
                    s_r <= 0;
                    
                    // s = N-2
                    a1_op1 <= N;
                    a1_op2 <= -2;
                    
                    state_r <= CMP_S;
                end
            CMP_S:
                begin
                    s_r <= a1_res;
                    if(a1_res > -3) begin
                        y_r = y_r << 1;
                        
                        // 3*y
                        m1_op1 <= 3;
                        m1_op2 <= y_r;
                        m1_start <= 1;
                        
                        // y+1
                        a1_op1 <= y_r;
                        a1_op2 <= 1;
                        
                        state_r <= CALC_MULT_S1_START;
                        
                    end else begin
                        y1 <= y_r;
                        m1_start <= 0;                       
                        state_r <= CALC_MULT_S3;
                    end
                end
            CALC_MULT_S3:
                if(m1_busy == 0) begin
                    m1_op1 <= y1;
                    m1_op2 <= y_bi;
                    m1_start <= 1;
                    state_r <= FINISH_START;
                end
            FINISH_START:
                begin
                    m1_start <= 0;
                    state_r <= FINISH;
                end
            FINISH:
                if(m1_busy == 0) begin
                    y_bo <= m1_res;
                    rdy_o <= 1;

                    state_r <= IDLE;
                end
            CALC_MULT_S1_START: //waiting 1 clk for starting of the mult module
                begin
                    m1_start <= 0;
                    state_r <= CALC_MULT_S1;
                end
            CALC_MULT_S1:
                if(m1_busy == 0) begin
                    // m1_res = 3*y
                    // a1_res = y+1
                    // m1_res * a1_res = 3*y*(y+1)
                    m1_op1 <= m1_res;
                    m1_op2 <= a1_res;
                    m1_start <= 1;
                    
                    state_r <= CALC_MULT_S2_START;
                end
            CALC_MULT_S2_START: //waiting 1 clk for starting of the mult module
                begin
                    m1_start <= 0;
                    state_r <= CALC_MULT_S2;
                end
            CALC_MULT_S2:
                if(m1_busy == 0) begin
                    // 3*y(y+1)+1
                    a1_op1 <= m1_res;
                    a1_op2 <= 1;
                    
                    state_r <= CALC_B;
                end
            CALC_B:
                begin
                    b_r <= a1_res << s_r;
                    state_r <= CMP_B;
                end
            CMP_B:
                if(x_r >= b_r) begin
                    // x-b
                    a1_op1 <= x_r;
                    a1_op2 <= -b_r;
                    
                    // y+1
                    a2_op1 <= y_r;
                    a2_op2 <= 1;
                    
                    state_r <= CALC_S;
                    
                end else begin
                    state_r <= CALC_S;
                end
            CALC_S:
                begin
                    if(x_r >= b_r) begin
                        //x = x-b
                        x_r <= a1_res;
                        
                        //y = y+1
                        y_r <= a2_res;
                    end
                    
                    // s-3
                    a1_op1 <= s_r;
                    a1_op2 <= -3;
                    
                    state_r <= CMP_S;
                end
        endcase
    end

endmodule

2023.3-2023.7/Functional Electronic Circuits/Lab3/dev_tb.v
`include "dev.v"
`timescale 1ns/1ps

module dev_tb;


reg [31:0] a,b;
reg clk, rst;
reg start;

wire rdy;
wire [31:0] y;

dev uut(
    .clk_i(clk),
    .rst_i(rst),
    
    .x_bi(b),
    .y_bi(a),
    .start_i(start),

    .y_bo(y),
    .rdy_o(rdy)
);

always #5 clk = ~clk;

initial begin
    
    $dumpfile("time.vcd");
    $dumpvars(0, dev_tb);

    clk   = 0;
    rst   = 1;
    a     = 4;
    b     = 8;
    start = 0;

    #20
    rst   = 0;
    start = 1;
    #20
    start = 0;

    @(posedge rdy);
    #1000
    $finish;
        
end



endmodule

2023.3-2023.7/Functional Electronic Circuits/Lab3/time.vcd
$date
	Sun Jun 04 17:26:23 2023
$end
$version
	Icarus Verilog
$end
$timescale
	1ps
$end
$scope module dev_tb $end
$var wire 32 ! y [31:0] $end
$var wire 1 " rdy $end
$var reg 32 # a [31:0] $end
$var reg 32 $ b [31:0] $end
$var reg 1 % clk $end
$var reg 1 & rst $end
$var reg 1 ' start $end
$scope module uut $end
$var wire 1 % clk_i $end
$var wire 1 & rst_i $end
$var wire 1 ' start_i $end
$var wire 32 ( x_bi [31:0] $end
$var wire 32 ) y_bi [31:0] $end
$var wire 16 * m1_res16 [15:0] $end
$var wire 32 + m1_res [31:0] $end
$var wire 1 , m1_busy $end
$var wire 32 - a2_res [31:0] $end
$var wire 32 . a1_res [31:0] $end
$var parameter 32 / CALC_B $end
$var parameter 32 0 CALC_MULT_S1 $end
$var parameter 32 1 CALC_MULT_S1_START $end
$var parameter 32 2 CALC_MULT_S2 $end
$var parameter 32 3 CALC_MULT_S2_START $end
$var parameter 32 4 CALC_MULT_S3 $end
$var parameter 32 5 CALC_S $end
$var parameter 32 6 CMP_B $end
$var parameter 32 7 CMP_S $end
$var parameter 32 8 FINISH $end
$var parameter 32 9 FINISH_START $end
$var parameter 32 : IDLE $end
$var parameter 32 ; N $end
$var reg 32 < a1_op1 [31:0] $end
$var reg 32 = a1_op2 [31:0] $end
$var reg 32 > a2_op1 [31:0] $end
$var reg 32 ? a2_op2 [31:0] $end
$var reg 32 @ b_r [31:0] $end
$var reg 32 A m1_op1 [31:0] $end
$var reg 32 B m1_op2 [31:0] $end
$var reg 1 C m1_start $end
$var reg 1 " rdy_o $end
$var reg 32 D s_r [31:0] $end
$var reg 4 E state_r [3:0] $end
$var reg 32 F x_r [31:0] $end
$var reg 32 G y1 [31:0] $end
$var reg 32 H y_bo [31:0] $end
$var reg 32 I y_r [31:0] $end
$scope module a1 $end
$var wire 32 J a_bi [31:0] $end
$var wire 32 K b_bi [31:0] $end
$var wire 32 L c_bo [31:0] $end
$upscope $end
$scope module a2 $end
$var wire 32 M a_bi [31:0] $end
$var wire 32 N b_bi [31:0] $end
$var wire 32 O c_bo [31:0] $end
$upscope $end
$scope module m1 $end
$var wire 8 P a_bi [7:0] $end
$var wire 8 Q b_bi [7:0] $end
$var wire 1 % clk_i $end
$var wire 8 R part_sum [7:0] $end
$var wire 1 & rst_i $end
$var wire 1 C start_i $end
$var wire 16 S shifted_part_sum [15:0] $end
$var parameter 2 T END $end
$var parameter 2 U IDLE $end
$var parameter 2 V WORK $end
$var reg 8 W a [7:0] $end
$var reg 8 X b [7:0] $end
$var reg 1 , busy_o $end
$var reg 3 Y ctr [2:0] $end
$var reg 16 Z part_res [15:0] $end
$var reg 2 [ state [1:0] $end
$var reg 16 \ y_bo [15:0] $end
$upscope $end
$upscope $end
$upscope $end
$enddefinitions $end
$comment Show the parameter values. $end
$dumpall
b1 V
b0 U
b10 T
b100000 ;
b0 :
b1010 9
b1011 8
b1 7
b111 6
b1000 5
b1001 4
b100 3
b101 2
b10 1
b11 0
b110 /
$end
#0
$dumpvars
bx \
bx [
bx Z
bx Y
bx X
bx W
bx S
bx R
bx Q
bx P
bx O
bx N
bx M
bx L
bx K
bx J
bx I
bx H
bx G
bx F
bx E
bx D
xC
bx B
bx A
bx @
bx ?
bx >
bx =
bx <
bx .
bx -
x,
b0xxxxxxxxxxxxxxxx +
bx *
b100 )
b1000 (
0'
1&
0%
b1000 $
b100 #
x"
bx !
$end
#5000
b0 Q
b0 P
b0 [
0,
b0 +
b0 *
b0 \
b0 Z
b0xxxxxxxx S
b0 Y
b0 E
b0 G
b0 D
1"
b0 I
b0 !
b0 H
b0 -
b0 O
b0 ?
b0 N
b0 >
b0 M
b0 .
b0 L
b0 =
b0 K
b0 <
b0 J
0C
b0 B
b0 A
b0 F
1%
#10000
0%
#15000
1%
#20000
0%
1'
0&
#25000
b1 E
b11111111111111111111111111111110 =
b11111111111111111111111111111110 K
b11110 .
b11110 L
b100000 <
b100000 J
b0 @
0"
b1000 F
1%
#30000
0%
#35000
b11 P
b10 E
b1 =
b1 K
b1 .
b1 L
b0 <
b0 J
1C
b11 A
b11110 D
1%
#40000
0%
0'
#45000
b0 S
b0 R
1,
b0 X
b11 W
b1 [
b11 E
0C
1%
#50000
0%
#55000
b1 Y
1%
#60000
0%
#65000
b10 Y
1%
#70000
0%
#75000
b11 Y
1%
#80000
0%
#85000
b100 Y
1%
#90000
0%
#95000
b101 Y
1%
#100000
0%
#105000
b110 Y
1%
#110000
0%
#115000
b111 Y
1%
#120000
0%
#125000
b0 Y
b10 [
1%
#130000
0%
#135000
b0 [
0,
1%
#140000
0%
#145000
b1 Q
b0 P
b100 E
1C
b1 B
b0 A
1%
#150000
0%
#155000
b101 E
0C
1,
b1 X
b0 W
b1 [
1%
#160000
0%
#165000
b1 Y
1%
#170000
0%
#175000
b10 Y
1%
#180000
0%
#185000
b11 Y
1%
#190000
0%
#195000
b100 Y
1%
#200000
0%
#205000
b101 Y
1%
#210000
0%
#215000
b110 Y
1%
#220000
0%
#225000
b111 Y
1%
#230000
0%
#235000
b0 Y
b10 [
1%
#240000
0%
#245000
b0 [
0,
1%
#250000
0%
#255000
b110 E
1%
#260000
0%
#265000
b111 E
b1000000000000000000000000000000 @
1%
#270000
0%
#275000
b1000 E
1%
#280000
0%
#285000
b1 E
b11111111111111111111111111111101 =
b11111111111111111111111111111101 K
b11011 .
b11011 L
b11110 <
b11110 J
1%
#290000
0%
#295000
b0 Q
b11 P
b10 E
b1 =
b1 K
b1 .
b1 L
b0 <
b0 J
1C
b0 B
b11 A
b11011 D
1%
#300000
0%
#305000
1,
b0 X
b11 W
b1 [
b11 E
0C
1%
#310000
0%
#315000
b1 Y
1%
#320000
0%
#325000
b10 Y
1%
#330000
0%
#335000
b11 Y
1%
#340000
0%
#345000
b100 Y
1%
#350000
0%
#355000
b101 Y
1%
#360000
0%
#365000
b110 Y
1%
#370000
0%
#375000
b111 Y
1%
#380000
0%
#385000
b0 Y
b10 [
1%
#390000
0%
#395000
b0 [
0,
1%
#400000
0%
#405000
b1 Q
b0 P
b100 E
1C
b1 B
b0 A
1%
#410000
0%
#415000
b101 E
0C
1,
b1 X
b0 W
b1 [
1%
#420000
0%
#425000
b1 Y
1%
#430000
0%
#435000
b10 Y
1%
#440000
0%
#445000
b11 Y
1%
#450000
0%
#455000
b100 Y
1%
#460000
0%
#465000
b101 Y
1%
#470000
0%
#475000
b110 Y
1%
#480000
0%
#485000
b111 Y
1%
#490000
0%
#495000
b0 Y
b10 [
1%
#500000
0%
#505000
b0 [
0,
1%
#510000
0%
#515000
b110 E
1%
#520000
0%
#525000
b111 E
b1000000000000000000000000000 @
1%
#530000
0%
#535000
b1000 E
1%
#540000
0%
#545000
b1 E
b11111111111111111111111111111101 =
b11111111111111111111111111111101 K
b11000 .
b11000 L
b11011 <
b11011 J
1%
#550000
0%
#555000
b0 Q
b11 P
b10 E
b1 =
b1 K
b1 .
b1 L
b0 <
b0 J
1C
b0 B
b11 A
b11000 D
1%
#560000
0%
#565000
1,
b0 X
b11 W
b1 [
b11 E
0C
1%
#570000
0%
#575000
b1 Y
1%
#580000
0%
#585000
b10 Y
1%
#590000
0%
#595000
b11 Y
1%
#600000
0%
#605000
b100 Y
1%
#610000
0%
#615000
b101 Y
1%
#620000
0%
#625000
b110 Y
1%
#630000
0%
#635000
b111 Y
1%
#640000
0%
#645000
b0 Y
b10 [
1%
#650000
0%
#655000
b0 [
0,
1%
#660000
0%
#665000
b1 Q
b0 P
b100 E
1C
b1 B
b0 A
1%
#670000
0%
#675000
b101 E
0C
1,
b1 X
b0 W
b1 [
1%
#680000
0%
#685000
b1 Y
1%
#690000
0%
#695000
b10 Y
1%
#700000
0%
#705000
b11 Y
1%
#710000
0%
#715000
b100 Y
1%
#720000
0%
#725000
b101 Y
1%
#730000
0%
#735000
b110 Y
1%
#740000
0%
#745000
b111 Y
1%
#750000
0%
#755000
b0 Y
b10 [
1%
#760000
0%
#765000
b0 [
0,
1%
#770000
0%
#775000
b110 E
1%
#780000
0%
#785000
b111 E
b1000000000000000000000000 @
1%
#790000
0%
#795000
b1000 E
1%
#800000
0%
#805000
b1 E
b11111111111111111111111111111101 =
b11111111111111111111111111111101 K
b10101 .
b10101 L
b11000 <
b11000 J
1%
#810000
0%
#815000
b0 Q
b11 P
b10 E
b1 =
b1 K
b1 .
b1 L
b0 <
b0 J
1C
b0 B
b11 A
b10101 D
1%
#820000
0%
#825000
1,
b0 X
b11 W
b1 [
b11 E
0C
1%
#830000
0%
#835000
b1 Y
1%
#840000
0%
#845000
b10 Y
1%
#850000
0%
#855000
b11 Y
1%
#860000
0%
#865000
b100 Y
1%
#870000
0%
#875000
b101 Y
1%
#880000
0%
#885000
b110 Y
1%
#890000
0%
#895000
b111 Y
1%
#900000
0%
#905000
b0 Y
b10 [
1%
#910000
0%
#915000
b0 [
0,
1%
#920000
0%
#925000
b1 Q
b0 P
b100 E
1C
b1 B
b0 A
1%
#930000
0%
#935000
b101 E
0C
1,
b1 X
b0 W
b1 [
1%
#940000
0%
#945000
b1 Y
1%
#950000
0%
#955000
b10 Y
1%
#960000
0%
#965000
b11 Y
1%
#970000
0%
#975000
b100 Y
1%
#980000
0%
#985000
b101 Y
1%
#990000
0%
#995000
b110 Y
1%
#1000000
0%
#1005000
b111 Y
1%
#1010000
0%
#1015000
b0 Y
b10 [
1%
#1020000
0%
#1025000
b0 [
0,
1%
#1030000
0%
#1035000
b110 E
1%
#1040000
0%
#1045000
b111 E
b1000000000000000000000 @
1%
#1050000
0%
#1055000
b1000 E
1%
#1060000
0%
#1065000
b1 E
b11111111111111111111111111111101 =
b11111111111111111111111111111101 K
b10010 .
b10010 L
b10101 <
b10101 J
1%
#1070000
0%
#1075000
b0 Q
b11 P
b10 E
b1 =
b1 K
b1 .
b1 L
b0 <
b0 J
1C
b0 B
b11 A
b10010 D
1%
#1080000
0%
#1085000
1,
b0 X
b11 W
b1 [
b11 E
0C
1%
#1090000
0%
#1095000
b1 Y
1%
#1100000
0%
#1105000
b10 Y
1%
#1110000
0%
#1115000
b11 Y
1%
#1120000
0%
#1125000
b100 Y
1%
#1130000
0%
#1135000
b101 Y
1%
#1140000
0%
#1145000
b110 Y
1%
#1150000
0%
#1155000
b111 Y
1%
#1160000
0%
#1165000
b0 Y
b10 [
1%
#1170000
0%
#1175000
b0 [
0,
1%
#1180000
0%
#1185000
b1 Q
b0 P
b100 E
1C
b1 B
b0 A
1%
#1190000
0%
#1195000
b101 E
0C
1,
b1 X
b0 W
b1 [
1%
#1200000
0%
#1205000
b1 Y
1%
#1210000
0%
#1215000
b10 Y
1%
#1220000
0%
#1225000
b11 Y
1%
#1230000
0%
#1235000
b100 Y
1%
#1240000
0%
#1245000
b101 Y
1%
#1250000
0%
#1255000
b110 Y
1%
#1260000
0%
#1265000
b111 Y
1%
#1270000
0%
#1275000
b0 Y
b10 [
1%
#1280000
0%
#1285000
b0 [
0,
1%
#1290000
0%
#1295000
b110 E
1%
#1300000
0%
#1305000
b111 E
b1000000000000000000 @
1%
#1310000
0%
#1315000
b1000 E
1%
#1320000
0%
#1325000
b1 E
b11111111111111111111111111111101 =
b11111111111111111111111111111101 K
b1111 .
b1111 L
b10010 <
b10010 J
1%
#1330000
0%
#1335000
b0 Q
b11 P
b10 E
b1 =
b1 K
b1 .
b1 L
b0 <
b0 J
1C
b0 B
b11 A
b1111 D
1%
#1340000
0%
#1345000
1,
b0 X
b11 W
b1 [
b11 E
0C
1%
#1350000
0%
#1355000
b1 Y
1%
#1360000
0%
#1365000
b10 Y
1%
#1370000
0%
#1375000
b11 Y
1%
#1380000
0%
#1385000
b100 Y
1%
#1390000
0%
#1395000
b101 Y
1%
#1400000
0%
#1405000
b110 Y
1%
#1410000
0%
#1415000
b111 Y
1%
#1420000
0%
#1425000
b0 Y
b10 [
1%
#1430000
0%
#1435000
b0 [
0,
1%
#1440000
0%
#1445000
b1 Q
b0 P
b100 E
1C
b1 B
b0 A
1%
#1450000
0%
#1455000
b101 E
0C
1,
b1 X
b0 W
b1 [
1%
#1460000
0%
#1465000
b1 Y
1%
#1470000
0%
#1475000
b10 Y
1%
#1480000
0%
#1485000
b11 Y
1%
#1490000
0%
#1495000
b100 Y
1%
#1500000
0%
#1505000
b101 Y
1%
#1510000
0%
#1515000
b110 Y
1%
#1520000
0%
#1525000
b111 Y
1%
#1530000
0%
#1535000
b0 Y
b10 [
1%
#1540000
0%
#1545000
b0 [
0,
1%
#1550000
0%
#1555000
b110 E
1%
#1560000
0%
#1565000
b111 E
b1000000000000000 @
1%
#1570000
0%
#1575000
b1000 E
1%
#1580000
0%
#1585000
b1 E
b11111111111111111111111111111101 =
b11111111111111111111111111111101 K
b1100 .
b1100 L
b1111 <
b1111 J
1%
#1590000
0%
#1595000
b0 Q
b11 P
b10 E
b1 =
b1 K
b1 .
b1 L
b0 <
b0 J
1C
b0 B
b11 A
b1100 D
1%
#1600000
0%
#1605000
1,
b0 X
b11 W
b1 [
b11 E
0C
1%
#1610000
0%
#1615000
b1 Y
1%
#1620000
0%
#1625000
b10 Y
1%
#1630000
0%
#1635000
b11 Y
1%
#1640000
0%
#1645000
b100 Y
1%
#1650000
0%
#1655000
b101 Y
1%
#1660000
0%
#1665000
b110 Y
1%
#1670000
0%
#1675000
b111 Y
1%
#1680000
0%
#1685000
b0 Y
b10 [
1%
#1690000
0%
#1695000
b0 [
0,
1%
#1700000
0%
#1705000
b1 Q
b0 P
b100 E
1C
b1 B
b0 A
1%
#1710000
0%
#1715000
b101 E
0C
1,
b1 X
b0 W
b1 [
1%
#1720000
0%
#1725000
b1 Y
1%
#1730000
0%
#1735000
b10 Y
1%
#1740000
0%
#1745000
b11 Y
1%
#1750000
0%
#1755000
b100 Y
1%
#1760000
0%
#1765000
b101 Y
1%
#1770000
0%
#1775000
b110 Y
1%
#1780000
0%
#1785000
b111 Y
1%
#1790000
0%
#1795000
b0 Y
b10 [
1%
#1800000
0%
#1805000
b0 [
0,
1%
#1810000
0%
#1815000
b110 E
1%
#1820000
0%
#1825000
b111 E
b1000000000000 @
1%
#1830000
0%
#1835000
b1000 E
1%
#1840000
0%
#1845000
b1 E
b11111111111111111111111111111101 =
b11111111111111111111111111111101 K
b1001 .
b1001 L
b1100 <
b1100 J
1%
#1850000
0%
#1855000
b0 Q
b11 P
b10 E
b1 =
b1 K
b1 .
b1 L
b0 <
b0 J
1C
b0 B
b11 A
b1001 D
1%
#1860000
0%
#1865000
1,
b0 X
b11 W
b1 [
b11 E
0C
1%
#1870000
0%
#1875000
b1 Y
1%
#1880000
0%
#1885000
b10 Y
1%
#1890000
0%
#1895000
b11 Y
1%
#1900000
0%
#1905000
b100 Y
1%
#1910000
0%
#1915000
b101 Y
1%
#1920000
0%
#1925000
b110 Y
1%
#1930000
0%
#1935000
b111 Y
1%
#1940000
0%
#1945000
b0 Y
b10 [
1%
#1950000
0%
#1955000
b0 [
0,
1%
#1960000
0%
#1965000
b1 Q
b0 P
b100 E
1C
b1 B
b0 A
1%
#1970000
0%
#1975000
b101 E
0C
1,
b1 X
b0 W
b1 [
1%
#1980000
0%
#1985000
b1 Y
1%
#1990000
0%
#1995000
b10 Y
1%
#2000000
0%
#2005000
b11 Y
1%
#2010000
0%
#2015000
b100 Y
1%
#2020000
0%
#2025000
b101 Y
1%
#2030000
0%
#2035000
b110 Y
1%
#2040000
0%
#2045000
b111 Y
1%
#2050000
0%
#2055000
b0 Y
b10 [
1%
#2060000
0%
#2065000
b0 [
0,
1%
#2070000
0%
#2075000
b110 E
1%
#2080000
0%
#2085000
b111 E
b1000000000 @
1%
#2090000
0%
#2095000
b1000 E
1%
#2100000
0%
#2105000
b1 E
b11111111111111111111111111111101 =
b11111111111111111111111111111101 K
b110 .
b110 L
b1001 <
b1001 J
1%
#2110000
0%
#2115000
b0 Q
b11 P
b10 E
b1 =
b1 K
b1 .
b1 L
b0 <
b0 J
1C
b0 B
b11 A
b110 D
1%
#2120000
0%
#2125000
1,
b0 X
b11 W
b1 [
b11 E
0C
1%
#2130000
0%
#2135000
b1 Y
1%
#2140000
0%
#2145000
b10 Y
1%
#2150000
0%
#2155000
b11 Y
1%
#2160000
0%
#2165000
b100 Y
1%
#2170000
0%
#2175000
b101 Y
1%
#2180000
0%
#2185000
b110 Y
1%
#2190000
0%
#2195000
b111 Y
1%
#2200000
0%
#2205000
b0 Y
b10 [
1%
#2210000
0%
#2215000
b0 [
0,
1%
#2220000
0%
#2225000
b1 Q
b0 P
b100 E
1C
b1 B
b0 A
1%
#2230000
0%
#2235000
b101 E
0C
1,
b1 X
b0 W
b1 [
1%
#2240000
0%
#2245000
b1 Y
1%
#2250000
0%
#2255000
b10 Y
1%
#2260000
0%
#2265000
b11 Y
1%
#2270000
0%
#2275000
b100 Y
1%
#2280000
0%
#2285000
b101 Y
1%
#2290000
0%
#2295000
b110 Y
1%
#2300000
0%
#2305000
b111 Y
1%
#2310000
0%
#2315000
b0 Y
b10 [
1%
#2320000
0%
#2325000
b0 [
0,
1%
#2330000
0%
#2335000
b110 E
1%
#2340000
0%
#2345000
b111 E
b1000000 @
1%
#2350000
0%
#2355000
b1000 E
1%
#2360000
0%
#2365000
b1 E
b11111111111111111111111111111101 =
b11111111111111111111111111111101 K
b11 .
b11 L
b110 <
b110 J
1%
#2370000
0%
#2375000
b0 Q
b11 P
b10 E
b1 =
b1 K
b1 .
b1 L
b0 <
b0 J
1C
b0 B
b11 A
b11 D
1%
#2380000
0%
#2385000
1,
b0 X
b11 W
b1 [
b11 E
0C
1%
#2390000
0%
#2395000
b1 Y
1%
#2400000
0%
#2405000
b10 Y
1%
#2410000
0%
#2415000
b11 Y
1%
#2420000
0%
#2425000
b100 Y
1%
#2430000
0%
#2435000
b101 Y
1%
#2440000
0%
#2445000
b110 Y
1%
#2450000
0%
#2455000
b111 Y
1%
#2460000
0%
#2465000
b0 Y
b10 [
1%
#2470000
0%
#2475000
b0 [
0,
1%
#2480000
0%
#2485000
b1 Q
b0 P
b100 E
1C
b1 B
b0 A
1%
#2490000
0%
#2495000
b101 E
0C
1,
b1 X
b0 W
b1 [
1%
#2500000
0%
#2505000
b1 Y
1%
#2510000
0%
#2515000
b10 Y
1%
#2520000
0%
#2525000
b11 Y
1%
#2530000
0%
#2535000
b100 Y
1%
#2540000
0%
#2545000
b101 Y
1%
#2550000
0%
#2555000
b110 Y
1%
#2560000
0%
#2565000
b111 Y
1%
#2570000
0%
#2575000
b0 Y
b10 [
1%
#2580000
0%
#2585000
b0 [
0,
1%
#2590000
0%
#2595000
b110 E
1%
#2600000
0%
#2605000
b111 E
b1000 @
1%
#2610000
0%
#2615000
b1000 E
b1 -
b1 O
b1 ?
b1 N
b11111111111111111111111111111000 =
b11111111111111111111111111111000 K
b0 .
b0 L
b1000 <
b1000 J
1%
#2620000
0%
#2625000
b1 E
b11111111111111111111111111111101 =
b11111111111111111111111111111101 K
b0 .
b0 L
b11 <
b11 J
b1 I
b0 F
1%
#2630000
0%
#2635000
b10 Q
b11 P
b10 E
b1 =
b1 K
b11 .
b11 L
b10 <
b10 J
1C
b10 B
b11 A
b0 D
b10 I
1%
#2640000
0%
#2645000
1,
b10 X
b11 W
b1 [
b11 E
0C
1%
#2650000
0%
#2655000
b110 S
b11 R
b1 Y
1%
#2660000
0%
#2665000
b0 R
b0 S
b10 Y
b110 Z
1%
#2670000
0%
#2675000
b11 Y
1%
#2680000
0%
#2685000
b100 Y
1%
#2690000
0%
#2695000
b101 Y
1%
#2700000
0%
#2705000
b110 Y
1%
#2710000
0%
#2715000
b111 Y
1%
#2720000
0%
#2725000
b0 Y
b10 [
1%
#2730000
0%
#2735000
b0 [
0,
b110 +
b110 *
b110 \
1%
#2740000
0%
#2745000
b11 Q
b110 P
b100 E
1C
b11 B
b110 A
1%
#2750000
0%
#2755000
b110 S
b110 R
b101 E
0C
1,
b0 Z
b11 X
b110 W
b1 [
1%
#2760000
0%
#2765000
b1100 S
b1 Y
b110 Z
1%
#2770000
0%
#2775000
b0 R
b0 S
b10 Y
b10010 Z
1%
#2780000
0%
#2785000
b11 Y
1%
#2790000
0%
#2795000
b100 Y
1%
#2800000
0%
#2805000
b101 Y
1%
#2810000
0%
#2815000
b110 Y
1%
#2820000
0%
#2825000
b111 Y
1%
#2830000
0%
#2835000
b110 S
b110 R
b0 Y
b10 [
1%
#2840000
0%
#2845000
b0 [
0,
b10010 +
b10010 *
b10010 \
1%
#2850000
0%
#2855000
b110 E
b10011 .
b10011 L
b10010 <
b10010 J
1%
#2860000
0%
#2865000
b111 E
b10011 @
1%
#2870000
0%
#2875000
b1000 E
1%
#2880000
0%
#2885000
b1 E
b11111111111111111111111111111101 =
b11111111111111111111111111111101 K
b11111111111111111111111111111101 .
b11111111111111111111111111111101 L
b0 <
b0 J
1%
#2890000
0%
#2895000
b1001 E
b10 G
b11111111111111111111111111111101 D
1%
#2900000
0%
#2905000
b100 Q
b10 P
b1010 E
1C
b100 B
b10 A
1%
#2910000
0%
#2915000
b0 S
b0 R
b1011 E
0C
1,
b0 Z
b100 X
b10 W
b1 [
1%
#2920000
0%
#2925000
b1 Y
1%
#2930000
0%
#2935000
b1000 S
b10 R
b10 Y
1%
#2940000
0%
#2945000
b0 R
b0 S
b11 Y
b1000 Z
1%
#2950000
0%
#2955000
b100 Y
1%
#2960000
0%
#2965000
b101 Y
1%
#2970000
0%
#2975000
b110 Y
1%
#2980000
0%
#2985000
b111 Y
1%
#2990000
0%
#2995000
b0 Y
b10 [
1%
#3000000
0%
#3005000
b0 [
0,
b1000 +
b1000 *
b1000 \
1%
#3010000
0%
#3015000
b0 E
1"
b1000 !
b1000 H
1%
