2023.3-2023.7/Functional Electronic Circuits/Lab1/dev.v
module dev(
    input [31:0] x,
    input start,
    input rst,
    input clk,
    output reg rd,
    output reg [31:0] y,
    output reg rdy
);

parameter N= 10;
parameter IDLE = 0;
parameter CALC = 1;


reg state;
reg[2:0] ctr;

always@(posedge clk)
    if(rst) begin
        state <= IDLE;
        ctr <= 0;
        rdy <= 1;
        rd <= 0;
        y <= 1;
    end else begin
        case(state)
            IDLE:
                if(start) begin
                    state <= CALC;
                    rdy <= 0;
                    rd <= 1;
                end
            CALC:
                begin
	  	    ctr <= ctr + 1;
				y<=(y << x) | (y >> (32 - x));

	     if(ctr == (N-1))begin
    	          rd <= 0;
	          state <= IDLE;
	          rdy = 1;
	     end
	     end

            endcase
        end

endmodule

2023.3-2023.7/Functional Electronic Circuits/Lab1/dev_tb.v
`timescale 1ns/1ps

module dev_tb;

reg [31:0] x;
reg start,rst,clk;
wire rd, rdy;
wire [31:0] y;

dev uut(
    .x(x),
    .rd(rd),
    .start(start),
    .rst(rst),
    .clk(clk),
    .y(y),
    .rdy(rdy)
);

always #5 clk = ~clk; // each 5 ns we will get opposite value of clk sigr

always@(negedge clk)
    if(rd)
        x = ($random % 10) & 8'hFF;

initial begin
    $dumpfile("time.vcd");
    $dumpvars(1, dev_tb);
    clk = 0;
    rst = 1;
    start = 0;
    x = 0;
    #20
    rst = 0;
    #20
    start = 1;
    #10
    start = 0;
    #250
    $finish;
end

endmodule

2023.3-2023.7/Functional Electronic Circuits/Lab1/time.vcd
$date
	Sat Apr 15 20:01:47 2023
$end
$version
	Icarus Verilog
$end
$timescale
	1ps
$end
$scope module dev_tb $end
$var wire 32 ! y [31:0] $end
$var wire 1 " rdy $end
$var wire 1 # rd $end
$var reg 1 $ clk $end
$var reg 1 % rst $end
$var reg 1 & start $end
$var reg 32 ' x [31:0] $end
$upscope $end
$enddefinitions $end
$comment Show the parameter values. $end
$dumpall
$end
#0
$dumpvars
b0 '
0&
1%
0$
x#
x"
bx !
$end
#5000
b1 !
0#
1"
1$
#10000
0$
#15000
1$
#20000
0$
0%
#25000
1$
#30000
0$
#35000
1$
#40000
0$
1&
#45000
1#
0"
1$
#50000
b1000 '
0$
0&
#55000
b100000000 !
1$
#60000
b111 '
0$
#65000
b1000000000000000 !
1$
#70000
0$
#75000
b10000000000000000000000 !
1$
#80000
0$
#85000
b100000000000000000000000000000 !
1$
#90000
0$
#95000
b10000 !
1$
#100000
0$
#105000
b100000000000 !
1$
#110000
b101 '
0$
#115000
b10000000000000000 !
1$
#120000
b10 '
0$
#125000
b1000000000000000000 !
1$
#130000
b1 '
0$
#135000
b10000000000000000000 !
1$
#140000
b1001 '
0$
#145000
b10000000000000000000000000000 !
1$
#150000
b1000 '
0$
#155000
b10000 !
1$
#160000
b111 '
0$
#165000
b100000000000 !
1$
#170000
b1001 '
0$
#175000
b100000000000000000000 !
1$
#180000
b10 '
0$
#185000
b10000000000000000000000 !
1$
#190000
b1001 '
0$
#195000
b10000000000000000000000000000000 !
1$
#200000
b110 '
0$
#205000
b100000 !
1$
#210000
b111 '
0$
#215000
b1000000000000 !
1$
#220000
b10 '
0$
#225000
b100000000000000 !
1$
#230000
b101 '
0$
#235000
b10000000000000000000 !
1$
#240000
0$
#245000
b1000000000000000000000000 !
1$
#250000
b100 '
0$
#255000
b10000000000000000000000000000 !
1$
#260000
b1001 '
0$
#265000
b100000 !
1$
#270000
b110 '
0$
#275000
b100000000000 !
1$
#280000
b0 '
0$
#285000
1$
#290000
b1000 '
0$
#295000
b10000000000000000000 !
1$
