2023.3-2023.7/Functional Electronic Circuits/Task1/.history/counter_20230415164244.v
module counter (
	input clk,
	input reset,
	input x1,
	output reg [31:0] result,
	reg [31:0] a
);

always@(posedge clk)
	a <= x1;
	if(reset)
		result <= 1;
	else if(a) begin
		result <= result << 1;
		a<=a-1;
	end
endmodule

2023.3-2023.7/Functional Electronic Circuits/Task1/.history/counter_tb_20230415162752.v
`timescale 1ns/1ns
module counter_tb;

	reg clk1;
    reg clk2;
	reg reset;
	wire [31:0] result1;
    wire [31:0] result2;

	counter dut1(
		.clk(clk1),
		.reset(reset),
		.result(result1)
	);

    counter dut2(
		.clk(clk2),
		.reset(reset),
		.result(result2)
	);

	always #5  clk1 = ~clk1; // inverting of clk1
    always #10 clk2 = ~clk2; // inverting of clk2

	initial begin

		$monitor("%t : %h", $time, result1);
		$dumpfile("time.vcd");
		$dumpvars(1, counter_tb);
		
        // set initial values
		clk1 = 0;
        clk2 = 0;
		reset  = 1;

		#100

		reset = 0;

		#1000

		$finish;
	end

endmodule

2023.3-2023.7/Functional Electronic Circuits/Task1/time.vcd
$date
	Sat Apr 15 16:28:01 2023
$end
$version
	Icarus Verilog
$end
$timescale
	1ns
$end
$scope module counter_tb $end
$var wire 32 ! result2 [31:0] $end
$var wire 32 " result1 [31:0] $end
$var reg 1 # clk1 $end
$var reg 1 $ clk2 $end
$var reg 1 % reset $end
$upscope $end
$enddefinitions $end
$comment Show the parameter values. $end
$dumpall
$end
#0
$dumpvars
1%
0$
0#
bx "
bx !
$end
#5
b1 "
1#
#10
b1 !
0#
1$
#15
1#
#20
0#
0$
#25
1#
#30
0#
1$
#35
1#
#40
0#
0$
#45
1#
#50
0#
1$
#55
1#
#60
0#
0$
#65
1#
#70
0#
1$
#75
1#
#80
0#
0$
#85
1#
#90
0#
1$
#95
1#
#100
0#
0$
0%
#105
b10 "
1#
#110
b10 !
0#
1$
#115
b100 "
1#
#120
0#
0$
#125
b1000 "
1#
#130
b100 !
0#
1$
#135
b10000 "
1#
#140
0#
0$
#145
b100000 "
1#
#150
b1000 !
0#
1$
#155
b1000000 "
1#
#160
0#
0$
#165
b10000000 "
1#
#170
b10000 !
0#
1$
#175
b100000000 "
1#
#180
0#
0$
#185
b1000000000 "
1#
#190
b100000 !
0#
1$
#195
b10000000000 "
1#
#200
0#
0$
#205
b100000000000 "
1#
#210
b1000000 !
0#
1$
#215
b1000000000000 "
1#
#220
0#
0$
#225
b10000000000000 "
1#
#230
b10000000 !
0#
1$
#235
b100000000000000 "
1#
#240
0#
0$
#245
b1000000000000000 "
1#
#250
b100000000 !
0#
1$
#255
b10000000000000000 "
1#
#260
0#
0$
#265
b100000000000000000 "
1#
#270
b1000000000 !
0#
1$
#275
b1000000000000000000 "
1#
#280
0#
0$
#285
b10000000000000000000 "
1#
#290
b10000000000 !
0#
1$
#295
b100000000000000000000 "
1#
#300
0#
0$
#305
b1000000000000000000000 "
1#
#310
b100000000000 !
0#
1$
#315
b10000000000000000000000 "
1#
#320
0#
0$
#325
b100000000000000000000000 "
1#
#330
b1000000000000 !
0#
1$
#335
b1000000000000000000000000 "
1#
#340
0#
0$
#345
b10000000000000000000000000 "
1#
#350
b10000000000000 !
0#
1$
#355
b100000000000000000000000000 "
1#
#360
0#
0$
#365
b1000000000000000000000000000 "
1#
#370
b100000000000000 !
0#
1$
#375
b10000000000000000000000000000 "
1#
#380
0#
0$
#385
b100000000000000000000000000000 "
1#
#390
b1000000000000000 !
0#
1$
#395
b1000000000000000000000000000000 "
1#
#400
0#
0$
#405
b10000000000000000000000000000000 "
1#
#410
b10000000000000000 !
0#
1$
#415
b0 "
1#
#420
0#
0$
#425
1#
#430
b100000000000000000 !
0#
1$
#435
1#
#440
0#
0$
#445
1#
#450
b1000000000000000000 !
0#
1$
#455
1#
#460
0#
0$
#465
1#
#470
b10000000000000000000 !
0#
1$
#475
1#
#480
0#
0$
#485
1#
#490
b100000000000000000000 !
0#
1$
#495
1#
#500
0#
0$
#505
1#
#510
b1000000000000000000000 !
0#
1$
#515
1#
#520
0#
0$
#525
1#
#530
b10000000000000000000000 !
0#
1$
#535
1#
#540
0#
0$
#545
1#
#550
b100000000000000000000000 !
0#
1$
#555
1#
#560
0#
0$
#565
1#
#570
b1000000000000000000000000 !
0#
1$
#575
1#
#580
0#
0$
#585
1#
#590
b10000000000000000000000000 !
0#
1$
#595
1#
#600
0#
0$
#605
1#
#610
b100000000000000000000000000 !
0#
1$
#615
1#
#620
0#
0$
#625
1#
#630
b1000000000000000000000000000 !
0#
1$
#635
1#
#640
0#
0$
#645
1#
#650
b10000000000000000000000000000 !
0#
1$
#655
1#
#660
0#
0$
#665
1#
#670
b100000000000000000000000000000 !
0#
1$
#675
1#
#680
0#
0$
#685
1#
#690
b1000000000000000000000000000000 !
0#
1$
#695
1#
#700
0#
0$
#705
1#
#710
b10000000000000000000000000000000 !
0#
1$
#715
1#
#720
0#
0$
#725
1#
#730
b0 !
0#
1$
